cyclic_toposort/__init__.py
cyclic_toposort/acyclic_toposort.py
cyclic_toposort/cyclic_toposort.py
cyclic_toposort/utils.py
cyclic_toposort-1.1.0.dist-info/METADATA
cyclic_toposort-1.1.0.dist-info/WHEEL
cyclic_toposort-1.1.0.dist-info/RECORD
