Metadata-Version: 2.1
Name: cyclic-toposort
Version: 1.1.0
Summary: A sorting algorithm for directed cyclic graphs that results in a sorting with minimal cyclic edges.
License: MIT
Author: Paul Pauls
Author-email: mail@paulpauls.de
Requires-Python: >=3.10,<4.0
Classifier: License :: OSI Approved :: MIT License
Classifier: Programming Language :: Python :: 3
Classifier: Programming Language :: Python :: 3.10
Classifier: Programming Language :: Python :: 3.11
